ConnectorDB-0.3.5.dist-info/DESCRIPTION.rst
ConnectorDB-0.3.5.dist-info/METADATA
ConnectorDB-0.3.5.dist-info/RECORD
ConnectorDB-0.3.5.dist-info/WHEEL
ConnectorDB-0.3.5.dist-info/metadata.json
ConnectorDB-0.3.5.dist-info/top_level.txt
connectordb/__init__.py
connectordb/_connection.py
connectordb/_connectordb.py
connectordb/_connectorobject.py
connectordb/_datapointarray.py
connectordb/_device.py
connectordb/_stream.py
connectordb/_user.py
connectordb/_websocket.py
connectordb/logger.py
connectordb/query/__init__.py
connectordb/query/dataset.py
connectordb/query/merge.py
connectordb/tools/__init__.py
